<?xml version="1.0"?>
<dynamic_timed_animation>
  <width>78</width>
  <height>126</height>
  <rootPath>resources/entities/sneak/</rootPath>
  <startConfig>smasherSouthWestStanding.xml</startConfig>
  <endConfig>smasherSouthWestStanding.xml</endConfig>
  <fileName>smasher_southwest_standing.png</fileName>
  <fileName>smasher_southwest_right.png</fileName>
  <fileName>smasher_southwest_standing.png</fileName>
  <fileName>smasher_southwest_left.png</fileName>
  <fileName>smasher_southwest_standing.png</fileName>
  <positioning>occupying</positioning>
</dynamic_timed_animation>
